rpc/__init__.py
rpc/client.py
rpc/server.py
rpc_Ariam27-0.1.0.dist-info/LICENSE
rpc_Ariam27-0.1.0.dist-info/METADATA
rpc_Ariam27-0.1.0.dist-info/WHEEL
rpc_Ariam27-0.1.0.dist-info/top_level.txt
rpc_Ariam27-0.1.0.dist-info/RECORD
