Metadata-Version: 2.1
Name: rpc-Ariam27
Version: 0.1.0
Summary: A simple rpc implementation
Home-page: https://github.com/Ariam27/rpc
Author: Ariam
Author-email: geniusariam@gmail.com
License: UNKNOWN
Project-URL: Bug Tracker, https://github.com/Ariam27/rpc/issues
Platform: UNKNOWN
Classifier: Programming Language :: Python :: 3
Classifier: License :: OSI Approved :: MIT License
Classifier: Operating System :: OS Independent
Requires-Python: >=3.6
License-File: LICENSE
